config_source.py
config_source-0.0.8.dist-info/LICENSE
config_source-0.0.8.dist-info/METADATA
config_source-0.0.8.dist-info/WHEEL
config_source-0.0.8.dist-info/top_level.txt
config_source-0.0.8.dist-info/RECORD
