Metadata-Version: 2.1
Name: config-source
Version: 0.0.8
Summary: Simple configurations management for applications.
Home-page: UNKNOWN
Author: Sergey Kozlov
Author-email: dev@ludditelabs.io
License: UNKNOWN
Platform: UNKNOWN
Classifier: Development Status :: 4 - Beta
Classifier: License :: OSI Approved :: Apache Software License
Classifier: Intended Audience :: Developers
Classifier: Programming Language :: Python
Classifier: Programming Language :: Python :: 2.7
Classifier: Programming Language :: Python :: 3
Classifier: Topic :: Software Development :: Libraries :: Python Modules
Classifier: Topic :: Utilities
Requires-Dist: future (>=0.16.0)
